.gitignore
LICENSE.txt
MANIFEST.in
README.md
setup.py
h5dj/__init__.py
h5dj/__init__.pyc
h5dj/models.py
h5dj/storage.py
hdf5_django.egg-info/PKG-INFO
hdf5_django.egg-info/SOURCES.txt
hdf5_django.egg-info/dependency_links.txt
hdf5_django.egg-info/entry_points.txt
hdf5_django.egg-info/namespace_packages.txt
hdf5_django.egg-info/requires.txt
hdf5_django.egg-info/top_level.txt
tests/__init__.py
tests/runtests.py
tests/test_settings.py
tests/h5dj_tests/__init__.py
tests/h5dj_tests/tests.py
tests/images/2805163544_1321ee6d30_o.jpg
tests/images/After_The_Quake_Detail_Text_2to3_000.jpg
tests/images/IMG_1310.jpg
tests/images/IfThen_Detail_Computron_Orange_2to3_010.jpg
tests/images/IfThen_Detail_Computron_Silver_2to3_010.jpg
tests/images/Josef_Muller_Brockmann_Detail_Lights_2to3_000.jpg
tests/images/P4141469.jpg
tests/images/P4141472.jpg
tests/images/P4141477.jpg
tests/images/P4141870.jpg