Metadata-Version: 1.1
Name: hdf5-django
Version: 0.1.2
Summary: HDF5 interfaces for Django
Home-page: http://github.com/fish2000/h5dj/
Author: Alexander Bohn
Author-email: fish2000@gmail.com
License: BSD
Keywords: imaging,image analysis,image comparison,image processing,django,numpy,arrays,matrix,storage
Platform: UNKNOWN
Classifier: Development Status :: 4 - Beta
Classifier: Environment :: Web Environment
Classifier: Intended Audience :: Developers
Classifier: License :: OSI Approved :: BSD License
Classifier: Operating System :: OS Independent
Classifier: Programming Language :: Python :: 2.7
Classifier: Topic :: Utilities
